sqlmodel_crud_utilities-0.1.0.dist-info/licenses/LICENSE
sqlmodel_crud_utils/__init__.py
sqlmodel_crud_utils/a_sync.py
sqlmodel_crud_utils/sync.py
sqlmodel_crud_utils/utils.py
sqlmodel_crud_utilities-0.1.0.dist-info/METADATA
sqlmodel_crud_utilities-0.1.0.dist-info/WHEEL
sqlmodel_crud_utilities-0.1.0.dist-info/top_level.txt
sqlmodel_crud_utilities-0.1.0.dist-info/RECORD
