Metadata-Version: 2.4
Name: sqlmodel_crud_utilities
Version: 0.1.0
Summary: A set of CRUD utilities to expedite operations with SQLModel
Author-email: Francis Secada <francis.secada@gmail.com>
License-Expression: MIT AND (Apache-2.0 OR BSD-2-Clause)
Project-URL: Homepage, https://fsecada01.github.io/SQLModel-CRUD-Utilities/sqlmodel_crud_utils.html
Project-URL: Repository, https://github.com/fsecada01/sqlmodel_crud_utils
Project-URL: Bug Tracker, https://github.com/fsecada01/sqlmodel_crud_utils/issues
Classifier: Programming Language :: Python :: 3
Classifier: Operating System :: OS Independent
Requires-Python: >=3.9
License-File: LICENSE
Requires-Dist: loguru>=0.7.3
Requires-Dist: python-dateutil>=2.9.0.post0
Requires-Dist: python-dotenv>=1.1.0
Requires-Dist: sqlmodel>=0.0.24
Dynamic: license-file
